project_1.srcs/sources_1/new/pro_con.v
`timescale 1ns / 1ps
//////////////////////////////////////////////////////////////////////////////////
// Company: 
// Engineer: 
// 
// Create Date: 09/25/2020 08:58:06 PM
// Design Name: 
// Module Name: pro_con
// Project Name: 
// Target Devices: 
// Tool Versions: 
// Description: 
// 
// Dependencies: 
// 
// Revision:
// Revision 0.01 - File Created
// Additional Comments:
// 
//////////////////////////////////////////////////////////////////////////////////


module producer(producer_data, producer_iclk);
  input wire producer_iclk;
  output reg [3:0]producer_data;
  initial producer_data=0;
  always @(posedge producer_iclk) 
    begin
      producer_data = producer_data+1;
  end
endmodule

module consumer(consumer_iclk, consumer_data, consumer_req);
  input wire consumer_iclk;
  input [3:0] consumer_data;
  output reg consumer_req;
  initial consumer_req=0;
  always @(posedge consumer_iclk)
   begin
      consumer_req=~consumer_req;
     // $display("time=%t, consumer request=%d", $time, consumer_req);
    end
  
  endmodule

module fifo(producer_data, consumer_req, consumer_data);
  input [3:0] producer_data;
  input wire consumer_req;
  output reg [3:0] consumer_data;
  integer i;
  reg [3:0] memory[9:0];
  always@(producer_data)
    begin
     if(producer_data<=4'b1010)
       begin
       for(i=0;i<10;i=i+1)
         begin
           memory[i]=producer_data; 
         end
         //$display("time=%t, Producer data in fifo=%d", $time, producer_data);
       end
     else
       $finish;
    end
  always@(consumer_req)
    begin
      if(consumer_req==1)
         begin
           for(i=0; i<10; i=i+1)
               begin
                 consumer_data=memory[i];
               end
            //$display("time=%t, consumer data=%d", $time, consumer_data);
         end 
      else
        consumer_data=4'b0;
    end
  
endmodule

project_1.srcs/sim_1/new/pro_con_tb.v
`timescale 1ns / 1ps
//////////////////////////////////////////////////////////////////////////////////
// Company: 
// Engineer: 
// 
// Create Date: 09/26/2020 12:03:47 AM
// Design Name: 
// Module Name: pro_con_tb
// Project Name: 
// Target Devices: 
// Tool Versions: 
// Description: 
// 
// Dependencies: 
// 
// Revision:
// Revision 0.01 - File Created
// Additional Comments:
// 
//////////////////////////////////////////////////////////////////////////////////

module top;
  reg p_clock;//producer_clock
  reg c_clock;//consumer_clock
  wire [3:0] A;//producer_data
  wire [3:0] B;//consumer_data
  wire C;//consumer_req 1 bit
  producer pp(.producer_iclk(p_clock), .producer_data(A));
  consumer cc(.consumer_iclk(c_clock), .consumer_data(B), .consumer_req(C));
  fifo ff(.producer_data(A), .consumer_req(C), .consumer_data(B));
  initial
    begin
      $dumpfile("xyz.vcd");
      $dumpvars;
      p_clock=0;
      c_clock=0;
     #500 $finish;
    end
  always #10 p_clock=~p_clock;
  always #5 c_clock=~c_clock;
  always @(C)
   $display("TIME(in ns)=%t, producer's data=%d consumer_request=%d and consumer's data=%d", $time, A, C, B);
endmodule

project_1.sim/sim_1/behav/xsim/xyz.vcd
$date
   Sat Sep 26 00:05:36 2020
$end
$version
  2020.1
$end
$timescale
  1ps
$end
$scope module top $end
$var reg 1 ! p_clock $end
$var reg 1 " c_clock $end
$var wire 4 # A [3:0] $end
$var wire 4 $ B [3:0] $end
$var wire 1 % C $end
$scope module pp $end
$var wire 1 & producer_iclk $end
$var reg 4 ' producer_data [3:0] $end
$upscope $end
$scope module cc $end
$var wire 1 ( consumer_iclk $end
$var wire 4 $ consumer_data [3:0] $end
$var reg 1 ) consumer_req $end
$upscope $end
$scope module ff $end
$var wire 4 # producer_data [3:0] $end
$var wire 1 % consumer_req $end
$var reg 4 * consumer_data [3:0] $end
$var integer 32 + i $end
$upscope $end
$upscope $end
$enddefinitions $end
#0
$dumpvars
0!
0"
b0 #
b0 $
0%
0&
b0 '
0(
0)
b0 *
b1010 +
$end
#5000
1"
1%
1(
1)
b0 *
b1010 +
#10000
1!
0"
b1 #
1&
b1 '
0(
b1010 +
#15000
1"
0%
1(
0)
b0 *
#20000
0!
0"
0&
0(
#25000
1"
b1 $
1%
1(
1)
b1 *
b1010 +
#30000
1!
0"
b10 #
1&
b10 '
0(
b1010 +
#35000
1"
b0 $
0%
1(
0)
b0 *
#40000
0!
0"
0&
0(
#45000
1"
b10 $
1%
1(
1)
b10 *
b1010 +
#50000
1!
0"
b11 #
1&
b11 '
0(
b1010 +
#55000
1"
b0 $
0%
1(
0)
b0 *
#60000
0!
0"
0&
0(
#65000
1"
b11 $
1%
1(
1)
b11 *
b1010 +
#70000
1!
0"
b100 #
1&
b100 '
0(
b1010 +
#75000
1"
b0 $
0%
1(
0)
b0 *
#80000
0!
0"
0&
0(
#85000
1"
b100 $
1%
1(
1)
b100 *
b1010 +
#90000
1!
0"
b101 #
1&
b101 '
0(
b1010 +
#95000
1"
b0 $
0%
1(
0)
b0 *
#100000
0!
0"
0&
0(
#105000
1"
b101 $
1%
1(
1)
b101 *
b1010 +
#110000
1!
0"
b110 #
1&
b110 '
0(
b1010 +
#115000
1"
b0 $
0%
1(
0)
b0 *
#120000
0!
0"
0&
0(
#125000
1"
b110 $
1%
1(
1)
b110 *
b1010 +
#130000
1!
0"
b111 #
1&
b111 '
0(
b1010 +
#135000
1"
b0 $
0%
1(
0)
b0 *
#140000
0!
0"
0&
0(
#145000
1"
b111 $
1%
1(
1)
b111 *
b1010 +
#150000
1!
0"
b1000 #
1&
b1000 '
0(
b1010 +
#155000
1"
b0 $
0%
1(
0)
b0 *
#160000
0!
0"
0&
0(
#165000
1"
b1000 $
1%
1(
1)
b1000 *
b1010 +
#170000
1!
0"
b1001 #
1&
b1001 '
0(
b1010 +
#175000
1"
b0 $
0%
1(
0)
b0 *
#180000
0!
0"
0&
0(
#185000
1"
b1001 $
1%
1(
1)
b1001 *
b1010 +
#190000
1!
0"
b1010 #
1&
b1010 '
0(
b1010 +
#195000
1"
b0 $
0%
1(
0)
b0 *
#200000
0!
0"
0&
0(
#205000
1"
b1010 $
1%
1(
1)
b1010 *
b1010 +
